pimpmyplt/__init__.py
pimpmyplt/pimps/__init__.py
pimpmyplt/pimps/abc.py
pimpmyplt/pimps/color.py
pimpmyplt/pimps/figsize.py
pimpmyplt/pimps/savefig.py
pimpmyplt/pimps/text.py
pimpmyplt/pimps/tightlayout.py
pimpmyplt/pimps/usetex.py
pimpmyplt/util.py
pimpmyplt-0.0.6.dist-info/LICENSE
pimpmyplt-0.0.6.dist-info/METADATA
pimpmyplt-0.0.6.dist-info/WHEEL
pimpmyplt-0.0.6.dist-info/RECORD
