Metadata-Version: 2.1
Name: pimpmyplt
Version: 0.0.6
Summary: Pimp up my matplotlib plots
License: MIT
Author: Daniel Müller
Author-email: acct.d-mueller@mailbox.org
Requires-Python: >=3.12,<4.0
Classifier: License :: OSI Approved :: MIT License
Classifier: Programming Language :: Python :: 3
Classifier: Programming Language :: Python :: 3.12
